game_tools/__init__.py
game_tools/device/__init__.py
game_tools/device/cBezier.py
game_tools/device/windows.py
game_tools/device/windows_message.py
game_tools/fsm/__init__.py
game_tools/fsm/fsm_ex.py
game_tools/ocr/__init__.py
game_tools/ocr/ocr.py
game_tools/ocr/ocr_client.py
game_tools/recognition/__init__.py
game_tools/recognition/finds.py
game_tools/recognition/imageutls.py
game_tools/utils/__init__.py
game_tools/utils/config.py
game_tools/utils/game_logging.py
game_tools/utils/utils.py
shadow_game_tools-0.0.9.dist-info/METADATA
shadow_game_tools-0.0.9.dist-info/WHEEL
shadow_game_tools-0.0.9.dist-info/top_level.txt
shadow_game_tools-0.0.9.dist-info/RECORD
